{
    "routeId" : "14014",
    "name": "Glen Oaks Elementary",
    "timeOfDay": "morning",
    "coordinates": [
        {
            "time": "645",
            "location": "Parkridge Ave and Westfield Drive",
            "latitude": "33.453587",
            "longitude": "-86.931717"
        },
        {
            "time": "646",
            "location": "929 Westfield Drive",
            "latitude": "33.4527607",
            "longitude": "-86.9328747"
        },
        {
            "time": "647",
            "location": "817 Westfield Drive",
            "latitude": "33.4550845",
            "longitude": "-86.9352419"
        },
        {
            "time": "649",
            "location": "619 Westfield Drive",
            "latitude": "33.4579584",
            "longitude": "-86.9359271"
        },
        {
            "time": "651",
            "location": "1000 Hillandale Dr. (Oakland Dr. side)",
            "latitude": "33.454192",
            "longitude": "-86.93825"
        },
        {
            "time": "653",
            "location": "900 Glen Oaks Drive (Hillandale Dr. Side)",
            "latitude": "33.456554",
            "longitude": "-86.938988"
        },
        {
            "time": "654",
            "location": "1000 Glen Oaks Drive",
            "latitude": "33.455898",
            "longitude": "-86.93759"
        },
        {
            "time": "655",
            "location": "800 Glen Crest Dr. (Park Ave. side)",
            "latitude": "33.4557324",
            "longitude": "-86.9365814"
        },
        {
            "time": "656",
            "location": "846 Park Ave.",
            "latitude": "33.4544377",
            "longitude": "-86.9332322"
        },
        {
            "time": "657",
            "location": "824 Fairfax Drive",
            "latitude": "33.456371",
            "longitude": "-86.931393"
        },
        {
            "time": "658",
            "location": "407 Glen Crest Drive",
            "latitude": "33.457612",
            "longitude": "-86.930678"
        },
        {
            "time": "659",
            "location": "345 Glen Crest Drive",
            "latitude": "33.4576602",
            "longitude": "-86.9288008"
        },
        {
            "time": "702",
            "location": "1184 Red Oak Circle",
            "latitude": "33.4630312",
            "longitude": "-86.9285621"
        },
        {
            "time": "705",
            "location": "Millstead Road and Post Oak Circle",
            "latitude": "33.465333",
            "longitude": "-86.933394"
        },
        {
            "time": "706",
            "location": "1101 Cambridge Circle",
            "latitude": "33.466171",
            "longitude": "-86.930817"
        },
        {
            "time": "708",
            "location": "1420 Cambridge Blvd",
            "latitude": "33.4676734",
            "longitude": "-86.9309502"
        },
        {
            "time": "710",
            "location": "924 Live Oak Circle",
            "latitude": "33.464647",
            "longitude": "-86.93562"
        },
        {
            "time": "711",
            "location": "400 Live Oak Circle",
            "latitude": "33.46264",
            "longitude": "-86.935342"
        },
        {
            "time": "713",
            "location": "1033 Grand Oaks Road",
            "latitude": "33.463132",
            "longitude": "-86.933453"
        },
        {
            "time": "714",
            "location": "1016 Griswold Road (Glenfair Dr. Side)",
            "latitude": "33.461876",
            "longitude": "-86.933304"
        },
        {
            "time": "716",
            "location": "604 Glen Park Drive",
            "latitude": "33.45959",
            "longitude": "-86.9342"
        },
        {
            "time": "717",
            "location": "644 Glen Park Drive",
            "latitude": "33.457521",
            "longitude": "-86.934149"
        },
        {
            "time": "719",
            "location": "700 Fairfax Drive",
            "latitude": "33.459878",
            "longitude": "-86.931756"
        },
        {
            "time": "721",
            "location": "Chateau Glen Oaks - stop sign facing Building 400",
            "latitude": "33.462371",
            "longitude": "-86.929708"
        },
        {
            "time": "727",
            "location": "GLEN OAKS ELEMENTARY SCHOOL",
            "latitude": "33.459835",
            "longitude": "-86.927923"
        }
    ]
}
